fortuned/__init__.py
fortuned/app.py
fortuned/templates/index.html
fortuned-1.0.2.dist-info/entry_points.txt
fortuned-1.0.2.dist-info/WHEEL
fortuned-1.0.2.dist-info/METADATA
fortuned-1.0.2.dist-info/RECORD
