Metadata-Version: 2.1
Name: fortuned
Version: 1.0.2
Summary: A fortune teller that doesn't really tell you your fortune.
Requires-Dist: flask
